PGAA/FastApproximate.py
PGAA/Jimenez.py
PGAA/Morphological.py
PGAA/ScharrNormalFilter.py
PGAA/SubpixelMorphological.py
PGAA/SuperSampling.py
PGAA/__init__.py
PGAA/_common.py
pgaa-3.1.1.dist-info/licenses/LICENSE.md
pgaa-3.1.1.dist-info/WHEEL
pgaa-3.1.1.dist-info/METADATA
pgaa-3.1.1.dist-info/RECORD
