Metadata-Version: 2.4
Name: PGAA
Version: 3.1.1
Summary: PGAA (Pygame-CE Anti-Aliasing) is a Python3 library that provides anti-aliasing for Pygame-CE sufaces.
Author-email: Adam Kudelas <adam.kudelas.pro@gmail.com>
Requires-Python: >=3.9
Classifier: Programming Language :: Python :: 3
Classifier: Programming Language :: Python :: 3.9
Classifier: Programming Language :: Python :: 3.10
Classifier: Programming Language :: Python :: 3.11
Classifier: Programming Language :: Python :: 3.12
Classifier: Programming Language :: Python :: 3.13
Classifier: Development Status :: 4 - Beta
Classifier: Intended Audience :: Developers
Classifier: Topic :: Software Development :: Libraries :: pygame
Classifier: Topic :: Games/Entertainment
Classifier: Topic :: Multimedia :: Graphics
License-File: LICENSE.md
Requires-Dist: pygame-ce >=2.4.0, <3
Requires-Dist: numpy >= 1.24.1, <2.5
Project-URL: Homepage, https://github.com/Iron-Sparrow/PGAA
